blastdns-1.5.3.dist-info/METADATA
blastdns-1.5.3.dist-info/WHEEL
blastdns.libs/libgcc_s-f5fcfe20.so.1
blastdns/__init__.py
blastdns/_native.cpython-312-i386-linux-musl.so
blastdns/client.py
blastdns/models.py
blastdns/tests/test_batching.py
blastdns/tests/test_client.py
blastdns/tests/test_mock_client.py
blastdns-1.5.3.dist-info/RECORD
