Metadata-Version: 2.4
Name: blastdns
Version: 1.5.3
Requires-Dist: orjson>=3.11.4
Requires-Dist: pydantic>=2.12.4
Summary: Async Python interface on top of the BlastDNS resolver
Keywords: dns,async,resolver,networking,osint
Author-email: TheTechromancer <thetechromancer@protonmail.com>
License-Expression: GPL-3.0
Requires-Python: >=3.9
